<?xml version="1.0" encoding="utf-8"?>
<Configuration>
  <Excluded>
    <exclude>.editorconfig</exclude>
    <exclude>.git</exclude>
    <exclude>.vs</exclude>
    <exclude>About\PublishedFileId.txt</exclude>
    <exclude>Assemblies\Stats.pdb</exclude>
    <exclude>Directory.Build.props</exclude>
    <exclude>GeneTable\Assemblies\GeneTable.pdb</exclude>
    <exclude>GeneTable\Source</exclude>
    <exclude>LICENSE</exclude>
    <exclude>README.md</exclude>
    <exclude>Source</exclude>
    <exclude>Stats.sln</exclude>
    <exclude>ThingTable\Assemblies\ThingTable.pdb</exclude>
    <exclude>ThingTable\Compat\Biotech\Assemblies\ThingTableBiotechCompat.pdb</exclude>
    <exclude>ThingTable\Compat\Biotech\Source</exclude>
    <exclude>ThingTable\Compat\CE\Assemblies\ThingTableCECompat.pdb</exclude>
    <exclude>ThingTable\Compat\CE\CombatExtended.dll</exclude>
    <exclude>ThingTable\Compat\CE\Source</exclude>
    <exclude>ThingTable\Source</exclude>
  </Excluded>
</Configuration>